drf_api_logger/__init__.py
drf_api_logger/admin.py
drf_api_logger/apps.py
drf_api_logger/collectstatic.py
drf_api_logger/events.py
drf_api_logger/insert_log_into_database.py
drf_api_logger/models.py
drf_api_logger/tests.py
drf_api_logger/utils.py
drf_api_logger/middleware/__init__.py
drf_api_logger/middleware/api_logger_middleware.py
drf_api_logger/migrations/0001_initial.py
drf_api_logger/migrations/0002_auto_20211221_2155.py
drf_api_logger/migrations/__init__.py
drf_api_logger/static/drf_api_logger/css/Chart.min.css
drf_api_logger/static/drf_api_logger/js/Chart.bundle.min.js
drf_api_logger/templates/change_form.html
drf_api_logger/templates/charts_change_list.html
drf_api_logger-1.1.21.dist-info/licenses/LICENSE
tests/__init__.py
tests/test_integration.py
tests/test_media_url_issue.py
tests/test_middleware.py
tests/test_models.py
tests/test_settings.py
tests/test_signals.py
tests/test_utils.py
tests/urls.py
drf_api_logger-1.1.21.dist-info/METADATA
drf_api_logger-1.1.21.dist-info/WHEEL
drf_api_logger-1.1.21.dist-info/top_level.txt
drf_api_logger-1.1.21.dist-info/RECORD
